solobot_web_api-1.0.1.dist-info/licenses/LICENSE
solowebapi/__init__.py
solowebapi/solowebapi.py
solobot_web_api-1.0.1.dist-info/METADATA
solobot_web_api-1.0.1.dist-info/WHEEL
solobot_web_api-1.0.1.dist-info/top_level.txt
solobot_web_api-1.0.1.dist-info/RECORD
